pyratebay/__init__.py
pyratebay/cli.py
pyratebay/config.py
pyratebay/data_fetcher.py
pyratebay/formatter.py
pyratebay/main.py
pyratebay/models.py
pyratebay-0.2.1.dist-info/licenses/LICENSE
pyratebay-0.2.1.dist-info/METADATA
pyratebay-0.2.1.dist-info/WHEEL
pyratebay-0.2.1.dist-info/entry_points.txt
pyratebay-0.2.1.dist-info/top_level.txt
pyratebay-0.2.1.dist-info/RECORD
