Metadata-Version: 2.4
Name: pyratebay
Version: 0.2.1
Summary: A simple command line tool for the pirate bay.
Author-email: EvilCult <void@evilcult.dev>
Maintainer: EvilCult
License:                                  Apache License
Project-URL: Homepage, https://github.com/evilcult/pyratebay
Project-URL: Source, https://github.com/evilcult/pyratebay
Project-URL: Issues, https://github.com/evilcult/pyratebay/issues
Keywords: piratebay,torrent,search
Classifier: Programming Language :: Python :: 3
Classifier: Programming Language :: Python :: 3.12
Classifier: License :: OSI Approved :: Apache Software License
Classifier: Development Status :: 4 - Beta
Classifier: Topic :: Multimedia :: Graphics
Requires-Python: >=3.12
License-File: LICENSE
Requires-Dist: requests>=2.32.5
Dynamic: license-file
